simple_mapillary/__init__.py
simple_mapillary/api/Client.py
simple_mapillary/api/__init__.py
simple_mapillary/api/api_utils.py
simple_mapillary/image/DetectionData.py
simple_mapillary/image/Image.py
simple_mapillary/image/ImageAPI.py
simple_mapillary/image/ImageData.py
simple_mapillary/image/__init__.py
simple_mapillary/image/detection_utils.py
simple_mapillary-0.0.4.dist-info/METADATA
simple_mapillary-0.0.4.dist-info/WHEEL
simple_mapillary-0.0.4.dist-info/top_level.txt
simple_mapillary-0.0.4.dist-info/RECORD
