Metadata-Version: 2.1
Name: simple-mapillary
Version: 0.0.4
Summary: Simplified Python library for accessing the Mapillary API.
Home-page: https://github.com/ibaiGorordo/simple-mapillary-python-sdk
Author: Ibai Gorordo
License: MIT
Requires-Dist: numpy
Requires-Dist: opencv-python
Requires-Dist: imread-from-url
Requires-Dist: requests
Requires-Dist: mapbox-vector-tile
